globalog/__init__.py
globalog/config.py
globalog/exceptions.py
globalog/logger.py
globalog-0.1.0.dist-info/METADATA
globalog-0.1.0.dist-info/WHEEL
globalog-0.1.0.dist-info/top_level.txt
globalog-0.1.0.dist-info/RECORD
