Metadata-Version: 2.1
Name: globalog
Version: 0.1.0
Summary: A global logger with automatic configuration loading
Author: Your Name
Project-URL: Homepage, https://github.com/ronpik/globalog
Classifier: Programming Language :: Python :: 3
Classifier: License :: OSI Approved :: MIT License
Classifier: Operating System :: OS Independent
Requires-Dist: PyYAML>=6.0.2
